AUTHORS
CHANGES.rst
COPYING
MANIFEST.in
README
README.rst
setup.py
update.sample
githooks/__init__.py
githooks/git.py
githooks/hg.py
githooks/launcher.py
githooks.egg-info/PKG-INFO
githooks.egg-info/SOURCES.txt
githooks.egg-info/dependency_links.txt
githooks.egg-info/entry_points.txt
githooks.egg-info/not-zip-safe
githooks.egg-info/requires.txt
githooks.egg-info/top_level.txt