Metadata-Version: 1.0
Name: githooks
Version: 0.5
Summary: Set of Git hooks for pep8, pyflakes, jslint and trac integration
Home-page: https://github.com/ablanco/githooks/
Author: Alejandro Blanco Escudero
Author-email: alejandro.b.e@gmail.com
License: GPL 3
Keywords: git hook pep8 pyflakes jslint trac
Platform: UNKNOWN
Classifier: Development Status :: 3 - Alpha
Classifier: Environment :: Console
Classifier: Intended Audience :: Developers
Classifier: Intended Audience :: System Administrators
Classifier: License :: OSI Approved :: GNU General Public License (GPL)
Classifier: Natural Language :: English
Classifier: Programming Language :: Python
Classifier: Programming Language :: JavaScript
Classifier: Topic :: Software Development :: Version Control
Classifier: Topic :: Software Development :: Quality Assurance
